{
	"info": {
		"_postman_id": "e1810051-ae6c-4b6b-a07b-1e1d58a3586c",
		"name": "UserHobbies",
		"schema": "https://schema.getpostman.com/json/collection/v2.1.0/collection.json"
	},
	"item": [
		{
			"name": "User",
			"item": [
				{
					"name": "Get All Users",
					"request": {
						"method": "GET",
						"header": [],
						"url": {
							"raw": "http://localhost:4000/api/v1/users",
							"protocol": "http",
							"host": [
								"localhost"
							],
							"port": "4000",
							"path": [
								"api",
								"v1",
								"users"
							]
						}
					},
					"response": []
				},
				{
					"name": "Create User",
					"request": {
						"method": "POST",
						"header": [],
						"body": {
							"mode": "raw",
							"raw": "{\r\n    \"name\": \"Sagar Betkar\"\r\n}",
							"options": {
								"raw": {
									"language": "json"
								}
							}
						},
						"url": {
							"raw": "http://localhost:4000/api/v1/create/user",
							"protocol": "http",
							"host": [
								"localhost"
							],
							"port": "4000",
							"path": [
								"api",
								"v1",
								"create",
								"user"
							]
						}
					},
					"response": []
				},
				{
					"name": "Update User",
					"request": {
						"method": "PUT",
						"header": [],
						"body": {
							"mode": "raw",
							"raw": "{\r\n    \"name\": \"Nick Betkar\"\r\n}",
							"options": {
								"raw": {
									"language": "json"
								}
							}
						},
						"url": {
							"raw": "http://localhost:4000/api/v1/update/user/62514466eaba7f015f44ba37",
							"protocol": "http",
							"host": [
								"localhost"
							],
							"port": "4000",
							"path": [
								"api",
								"v1",
								"update",
								"user",
								"62514466eaba7f015f44ba37"
							]
						}
					},
					"response": []
				},
				{
					"name": "Delete User",
					"request": {
						"method": "DELETE",
						"header": [],
						"url": {
							"raw": "http://localhost:4000/api/v1/delete/user/62514466eaba7f015f44ba37",
							"protocol": "http",
							"host": [
								"localhost"
							],
							"port": "4000",
							"path": [
								"api",
								"v1",
								"delete",
								"user",
								"62514466eaba7f015f44ba37"
							]
						}
					},
					"response": []
				}
			]
		},
		{
			"name": "Hobby",
			"item": [
				{
					"name": "Create Hobby for a user",
					"request": {
						"method": "POST",
						"header": [],
						"body": {
							"mode": "raw",
							"raw": "{\r\n    \"name\": \"Swiming\",\r\n    \"passionLevel\": \"high\",\r\n    \"year\": \"2019\"\r\n}",
							"options": {
								"raw": {
									"language": "json"
								}
							}
						},
						"url": {
							"raw": "http://localhost:4000/api/v1/625148c8df4b21982aa8f8cd/create/hobby",
							"protocol": "http",
							"host": [
								"localhost"
							],
							"port": "4000",
							"path": [
								"api",
								"v1",
								"625148c8df4b21982aa8f8cd",
								"create",
								"hobby"
							]
						}
					},
					"response": []
				},
				{
					"name": "Get all Users Hobbies",
					"request": {
						"method": "GET",
						"header": [],
						"url": {
							"raw": "http://localhost:4000/api/v1/hobbies",
							"protocol": "http",
							"host": [
								"localhost"
							],
							"port": "4000",
							"path": [
								"api",
								"v1",
								"hobbies"
							]
						}
					},
					"response": []
				},
				{
					"name": "Update hobby by Id",
					"request": {
						"method": "PUT",
						"header": [],
						"body": {
							"mode": "raw",
							"raw": "{\r\n    \"name\": \"Dancing\",\r\n    \"passionLevel\": \"high\",\r\n    \"year\": \"2019\"\r\n}",
							"options": {
								"raw": {
									"language": "json"
								}
							}
						},
						"url": {
							"raw": "http://localhost:4000/api/v1/update/hobby/6251482cdf4b21982aa8f8c4",
							"protocol": "http",
							"host": [
								"localhost"
							],
							"port": "4000",
							"path": [
								"api",
								"v1",
								"update",
								"hobby",
								"6251482cdf4b21982aa8f8c4"
							]
						}
					},
					"response": []
				},
				{
					"name": "Delete hobby",
					"request": {
						"method": "DELETE",
						"header": [],
						"url": {
							"raw": "http://localhost:4000/api/v1/delete/hobby/6251482cdf4b21982aa8f8c4",
							"protocol": "http",
							"host": [
								"localhost"
							],
							"port": "4000",
							"path": [
								"api",
								"v1",
								"delete",
								"hobby",
								"6251482cdf4b21982aa8f8c4"
							]
						}
					},
					"response": []
				}
			]
		}
	]
}